{
  "CreateFields": {
    "InputParams": [
      "Id",
      "StandardSrv",
      "ConnectionStrings",
      "NewProperty",
      "Links",
      "Name",
      "ApiKeys",
      "GroupId",
      "MongoDBVersion",
      "StateName",
      "CreateDate",
      "ProviderName",
      "ProviderSettings"
    ]
  },
  "ReadFields": {
    "InputParams": [
      "Id",
      "StandardSrv",
      "ConnectionStrings",
      "Name",
      "ApiKeys",
      "PageNum",
      "ItemsPerPage",
      "NewProperty",
      "Links",
      "Results",
      "TotalCount",
      "GroupId",
      "MongoDBVersion",
      "StateName",
      "CreateDate",
      "ProviderName",
      "ProviderSettings",
      "IncludeCount"
    ],
    "RequiredParams": ["GroupId", "Name"]
  },
  "UpdateFields": {},
  "DeleteFields": {
    "RequiredParams": ["GroupId", "Name"]
  },
  "ListFields": {}
}
